pyddragon/__init__.py
pyddragon/ddragon.py
pyddragon/request.py
pyddragon-0.1.0.dist-info/LICENSE
pyddragon-0.1.0.dist-info/METADATA
pyddragon-0.1.0.dist-info/WHEEL
pyddragon-0.1.0.dist-info/top_level.txt
pyddragon-0.1.0.dist-info/RECORD
