Metadata-Version: 2.1
Name: pyddragon
Version: 0.1.0
Summary: Python wrapper library providing LoL ddragon data asynchronously
Home-page: https://github.com/dp0973/pyddragon
Author: dp0973
Author-email: yeong0973@gmail.com
License: Apache 2.0
Platform: UNKNOWN
License-File: LICENSE
